cytopy/__init__.py
cytopy/data/__init__.py
cytopy/data/errors.py
cytopy/data/experiment.py
cytopy/data/fcs.py
cytopy/data/gate.py
cytopy/data/gating_strategy.py
cytopy/data/geometry.py
cytopy/data/mapping.py
cytopy/data/population.py
cytopy/data/project.py
cytopy/data/read_write.py
cytopy/data/setup.py
cytopy/data/subject.py
cytopy/feedback.py
cytopy/flow/__init__.py
cytopy/flow/build_models.py
cytopy/flow/cell_classifier/__init__.py
cytopy/flow/cell_classifier/cell_classifier.py
cytopy/flow/cell_classifier/keras_classifier.py
cytopy/flow/cell_classifier/sklearn_classifier.py
cytopy/flow/cell_classifier/utils.py
cytopy/flow/clustering/__init__.py
cytopy/flow/clustering/consensus.py
cytopy/flow/clustering/flowsom.py
cytopy/flow/clustering/main.py
cytopy/flow/dim_reduction.py
cytopy/flow/fda_norm.py
cytopy/flow/feature_selection.py
cytopy/flow/gate_search.py
cytopy/flow/neighbours.py
cytopy/flow/plotting/__init__.py
cytopy/flow/plotting/asinh_transform.py
cytopy/flow/plotting/embeddings_graphs.py
cytopy/flow/plotting/flow_plot.py
cytopy/flow/plotting/hlog_transform.py
cytopy/flow/plotting/logicle_transform.py
cytopy/flow/ref.py
cytopy/flow/sampling.py
cytopy/flow/transform.py
cytopy/flow/tree.py
cytopy/flow/variance.py
cytopy/tests/__init__.py
cytopy/tests/assets/.~lock.test_panel.xlsx#
cytopy/tests/assets/test.FCS
cytopy/tests/assets/test_panel.xlsx
cytopy/tests/conftest.py
cytopy/tests/test_assay_tools.py
cytopy/tests/test_clustering.py
cytopy/tests/test_experiment.py
cytopy/tests/test_fcs.py
cytopy/tests/test_gate.py
cytopy/tests/test_gating_strategy.py
cytopy/tests/test_geometry.py
cytopy/tests/test_mapping.py
cytopy/tests/test_plotting.py
cytopy/tests/test_population.py
cytopy/tests/test_project.py
cytopy/tests/test_read_write.py
cytopy/tests/test_ref.py
cytopy/tests/test_transform.py
cytopy/tests/test_utilities.py
cytopy-2.0.1.dist-info/LICENSE
cytopy-2.0.1.dist-info/WHEEL
cytopy-2.0.1.dist-info/METADATA
cytopy-2.0.1.dist-info/RECORD
