Metadata-Version: 2.1
Name: cytopy
Version: 2.0.1
Summary: Data centric algorithm agnostic cytometry analysis framework
License: MIT
Author: Ross Burton
Author-email: burtonrj@cardiff.ac.uk
Requires-Python: >=3.8,<4.0
Classifier: License :: OSI Approved :: MIT License
Classifier: Programming Language :: Python :: 3
Classifier: Programming Language :: Python :: 3.8
Classifier: Programming Language :: Python :: 3.9
Provides-Extra: docs
Requires-Dist: FlowIO (==0.9.5)
Requires-Dist: KDEpy (==1.0.10)
Requires-Dist: MiniSom (>=2.2.6,<3.0.0)
Requires-Dist: PhenoGraph (>=1.5.6,<2.0.0)
Requires-Dist: anytree (>=2.8,<3.0)
Requires-Dist: autodocsumm (>=0.2.1,<0.3.0)
Requires-Dist: cython (>=0.29,<0.30)
Requires-Dist: detecta (>=0.0.5,<0.0.6)
Requires-Dist: flowutils (==0.9.1)
Requires-Dist: future (>=0.18,<0.19)
Requires-Dist: graphviz (>=0.14,<0.15)
Requires-Dist: h5py (>=2.10,<3.0)
Requires-Dist: harmonypy (==0.0.5)
Requires-Dist: hdbscan (>=0.8,<0.9)
Requires-Dist: imbalanced-learn (>=0.7,<0.8)
Requires-Dist: ipython (==7.18.1)
Requires-Dist: loguru (>=0.5,<0.6)
Requires-Dist: matplotlib (>=3.3,<4.0)
Requires-Dist: mongoengine (>=0.20,<0.21)
Requires-Dist: nbconvert (>=6.0,<7.0)
Requires-Dist: networkx (>=2.5,<3.0)
Requires-Dist: oauthlib (>=3.1.0,<4.0.0)
Requires-Dist: openpyxl (==3.0.6)
Requires-Dist: pandas (>=1.1.2,<2.0.0)
Requires-Dist: phate (>=1.0.4,<2.0.0)
Requires-Dist: pingouin (>=0.3.8,<0.4.0)
Requires-Dist: python-dateutil (>=2.8.1,<3.0.0)
Requires-Dist: scikit-fda (==0.5)
Requires-Dist: scikit-learn (>=0.24.1,<0.25.0)
Requires-Dist: scipy (==1.6.0)
Requires-Dist: scprep (>=1.0,<2.0)
Requires-Dist: seaborn (>=0.11.0,<0.12.0)
Requires-Dist: setuptools (>=49.6.0,<50.0.0)
Requires-Dist: shap (==0.38.1)
Requires-Dist: shapely (==1.7.1)
Requires-Dist: snowballstemmer (>=2.0.0,<3.0.0)
Requires-Dist: sphinx (>=3,<4); extra == "docs"
Requires-Dist: statsmodels (>=0.12,<0.13)
Requires-Dist: tables (>=3.6.1,<4.0.0)
Requires-Dist: tensorflow (>=2.4,<3.0)
Requires-Dist: tqdm (>=4.49.0,<5.0.0)
Requires-Dist: umap-learn (>=0.4.6,<0.5.0)
Requires-Dist: uncertainties (>=3.1,<4.0)
Requires-Dist: xgboost (>=1.2.0,<2.0.0)
Requires-Dist: xlrd (>=1.2.0,<2.0.0)
Requires-Dist: yellowbrick (>=1.1,<2.0)
